encoder/__init__.py
encoder/encode.py
encodepacakge-0.0.7.dist-info/LICENSE
encodepacakge-0.0.7.dist-info/METADATA
encodepacakge-0.0.7.dist-info/WHEEL
encodepacakge-0.0.7.dist-info/top_level.txt
encodepacakge-0.0.7.dist-info/RECORD
