Metadata-Version: 2.1
Name: encodepacakge
Version: 0.0.7
Summary: encode string with given template
Home-page: https://github.com/uptownaravi/encoder
Author: uptownaravi
Author-email: uptownaravi@gmail.com
License: UNKNOWN
Platform: UNKNOWN
Classifier: Programming Language :: Python :: 3
Classifier: License :: OSI Approved :: MIT License
Classifier: Operating System :: OS Independent
License-File: LICENSE
